mycalc/calculator.py
jeongu-0.0.1.dist-info/METADATA
jeongu-0.0.1.dist-info/WHEEL
jeongu-0.0.1.dist-info/top_level.txt
jeongu-0.0.1.dist-info/RECORD
