Metadata-Version: 2.1
Name: jeongu
Version: 0.0.1
Summary: nice calculator
Home-page: https://github.com/P1anter/my-oss
Download-URL: https://github.com/P1anter/my-oss/
Author: jukim
Classifier: Programming Language :: Python :: 3
